agogosml/__init__.py
agogosml/common/__init__.py
agogosml/common/abstract_streaming_client.py
agogosml/common/broadcast_streaming_client.py
agogosml/common/eventhub_streaming_client.py
agogosml/common/flask_http_listener_client.py
agogosml/common/http_message_sender.py
agogosml/common/kafka_streaming_client.py
agogosml/common/listener_client.py
agogosml/common/message_sender.py
agogosml/common/redis_streaming_client.py
agogosml/common/storage_streaming_client.py
agogosml/reader/__init__.py
agogosml/reader/input_reader.py
agogosml/reader/input_reader_factory.py
agogosml/tools/__init__.py
agogosml/tools/receiver.py
agogosml/tools/sender.py
agogosml/utils/__init__.py
agogosml/utils/cli.py
agogosml/utils/config.py
agogosml/utils/http_request.py
agogosml/utils/imports.py
agogosml/utils/logger.py
agogosml/writer/__init__.py
agogosml/writer/output_writer.py
agogosml/writer/output_writer_factory.py
agogosml-0.1.3.dist-info/LICENSE
agogosml-0.1.3.dist-info/METADATA
agogosml-0.1.3.dist-info/WHEEL
agogosml-0.1.3.dist-info/top_level.txt
agogosml-0.1.3.dist-info/RECORD
