Metadata-Version: 2.1
Name: agogosml
Version: 0.1.3
Summary: Agogosml Library
Home-page: https://github.com/Microsoft/agogosml
Author: Rami Sayar
Author-email: rami.sayar@microsoft.com
License: MIT license
Keywords: agogosml
Platform: UNKNOWN
Classifier: Development Status :: 2 - Pre-Alpha
Classifier: Intended Audience :: Developers
Classifier: License :: OSI Approved :: MIT License
Classifier: Natural Language :: English
Classifier: Programming Language :: Python :: 3.7
Requires-Dist: confluent-kafka (~=0.11)
Requires-Dist: azure-eventhub (~=1.2)
Requires-Dist: requests (~=2.20)
Requires-Dist: redis (~=3.1.0)
Requires-Dist: python-dotenv (~=0.9)
Requires-Dist: flask (~=1.0.2)
Requires-Dist: pyyaml (>=4.2b1)
Requires-Dist: jsonschema (~=2.6)
Requires-Dist: applicationinsights (~=0.11.7)
Requires-Dist: cached-property (~=1.5.1)
Requires-Dist: singleton-decorator (~=1.0.0)
Requires-Dist: apache-libcloud (~=2.4.0)
